pyvotal5/__init__.py
pyvotal5/pyvotal.py
pyvotal5-0.0.2.dist-info/LICENSE
pyvotal5-0.0.2.dist-info/METADATA
pyvotal5-0.0.2.dist-info/WHEEL
pyvotal5-0.0.2.dist-info/top_level.txt
pyvotal5-0.0.2.dist-info/RECORD
