Metadata-Version: 2.1
Name: pyvotal5
Version: 0.0.2
Summary: lib for easy access to pivotal tracker's APIv5
Home-page: https://github.com/jjabba/pyvotal
Author: Karl Berggren
Author-email: kalle@jjabba.com
License: UNKNOWN
Platform: UNKNOWN
Classifier: Programming Language :: Python :: 3
Classifier: License :: OSI Approved :: MIT License
Classifier: Operating System :: OS Independent
Requires-Python: >=3.6
